{"cameraMode":{"drawMode":0,"name":"Shaded","section":"Shading Mode"},"sceneLighting":true,"audioPlay":false,"sceneViewState":{"m_AlwaysRefresh":false,"showFog":true,"showSkybox":true,"showFlares":true,"showImageEffects":true,"showParticleSystems":true,"showVisualEffectGraphs":true,"m_FxEnabled":true},"in2DMode":false,"pivot":{"x":50.0,"y":1.2769999504089356,"z":50.04800033569336},"rotation":{"x":0.17468608915805818,"y":-0.09321635216474533,"z":0.01659346930682659,"w":0.9800805449485779},"size":10.0,"orthographic":false}